winery/__init__.py
winery/templates.py
winery/wine.py
winery/backends/__init__.py
winery/backends/persistence/__init__.py
winery/backends/persistence/mariadb.py
winery/contracts/__init__.py
winery/contracts/persistence.py
winery/utils/__init__.py
winery/utils/dateutils.py
winery-0.2.0.dist-info/METADATA
winery-0.2.0.dist-info/WHEEL
winery-0.2.0.dist-info/entry_points.txt
winery-0.2.0.dist-info/licenses/LICENCE
winery-0.2.0.dist-info/RECORD
