Metadata-Version: 2.4
Name: winery
Version: 0.2.0
Summary: Winery toolchain
Author-email: Arian-Ott <arian.ott@ieee.org>
License-File: LICENCE
Requires-Python: >=3.10
Requires-Dist: jinja2>=3.1.6
Requires-Dist: pydantic[email]>=2.12.4
Requires-Dist: tzdata>=2025.2
Provides-Extra: dev
Requires-Dist: coverage>=7.11.3; extra == 'dev'
Requires-Dist: docker>=7.1.0; extra == 'dev'
Requires-Dist: freezegun>=1.5.5; extra == 'dev'
Requires-Dist: pygount>=3.1.0; extra == 'dev'
Requires-Dist: pytest-cov>=7.0.0; extra == 'dev'
Requires-Dist: pytest-order>=1.3.0; extra == 'dev'
Requires-Dist: pytest-xdist>=3.8.0; extra == 'dev'
Requires-Dist: pytest>=8.4.2; extra == 'dev'
Requires-Dist: ruff>=0.14.4; extra == 'dev'
Provides-Extra: maria
Requires-Dist: mariadb>=1.1.14; extra == 'maria'
